a_n_plus_b/__init__.py
a_n_plus_b/_a_n_plus_b.py
a_n_plus_b/_grammar.py
a_n_plus_b/_n.py
a_n_plus_b/py.typed
a_n_plus_b-0.2.0.dist-info/METADATA
a_n_plus_b-0.2.0.dist-info/WHEEL
a_n_plus_b-0.2.0.dist-info/licenses/LICENSE.txt
a_n_plus_b-0.2.0.dist-info/RECORD
