Metadata-Version: 2.3
Name: a-n-plus-b
Version: 0.2.0
Summary: CSS <An+B> microsyntax parser
Project-URL: Homepage, https://github.com/InSyncWithFoo/a-n-plus-b
Author-email: InSyncWithFoo <insyncwithfoo@gmail.com>
License: MIT
License-File: LICENSE.txt
Keywords: CSS,an+b,parser
Classifier: Development Status :: 3 - Alpha
Classifier: Intended Audience :: Developers
Classifier: License :: OSI Approved :: MIT License
Classifier: Programming Language :: Python :: 3
Classifier: Programming Language :: Python :: 3 :: Only
Classifier: Programming Language :: Python :: 3.10
Classifier: Programming Language :: Python :: 3.11
Classifier: Programming Language :: Python :: 3.12
Classifier: Programming Language :: Python :: Implementation :: CPython
Classifier: Topic :: Software Development :: Build Tools
Classifier: Typing :: Typed
Requires-Python: >=3.10
Requires-Dist: regex~=2023.12.25; python_version <= '3.10'
Provides-Extra: dev
Requires-Dist: hatch<1.13.0,>=1.9.3; extra == 'dev'
Requires-Dist: hypothesis<6.113,>=6.105.0; extra == 'dev'
Requires-Dist: mypy<1.12,>=1.8; extra == 'dev'
Requires-Dist: pyright~=1.1.347; extra == 'dev'
Requires-Dist: pytest-cov<5.1,>=4.1; extra == 'dev'
Requires-Dist: pytest<8.4,>=8.0; extra == 'dev'
Requires-Dist: ruff<0.7,>=0.5.0; extra == 'dev'
Requires-Dist: tox<4.21.0,>=4.16.0; extra == 'dev'
Requires-Dist: tzdata<2025.0,>=2023.4; extra == 'dev'
